dciclient/__init__.py
dciclient/create_component.py
dciclient/create_job.py
dciclient/diff_jobs.py
dciclient/find_latest_component.py
dciclient/printer.py
dciclient/rhel_kernel.py
dciclient/shell.py
dciclient/vault.py
dciclient/vault_client.py
dciclient/version.py
dciclient/v1/__init__.py
dciclient/v1/exceptions.py
dciclient/v1/utils.py
dciclient/v1/api/__init__.py
dciclient/v1/api/base.py
dciclient/v1/api/component.py
dciclient/v1/api/context.py
dciclient/v1/api/feeder.py
dciclient/v1/api/file.py
dciclient/v1/api/identity.py
dciclient/v1/api/job.py
dciclient/v1/api/jobs_events.py
dciclient/v1/api/jobstate.py
dciclient/v1/api/pipeline.py
dciclient/v1/api/product.py
dciclient/v1/api/remoteci.py
dciclient/v1/api/tag.py
dciclient/v1/api/team.py
dciclient/v1/api/topic.py
dciclient/v1/api/user.py
dciclient/v1/shell_commands/__init__.py
dciclient/v1/shell_commands/cli.py
dciclient/v1/shell_commands/columns.py
dciclient/v1/shell_commands/component.py
dciclient/v1/shell_commands/context.py
dciclient/v1/shell_commands/feeder.py
dciclient/v1/shell_commands/file.py
dciclient/v1/shell_commands/job.py
dciclient/v1/shell_commands/jobstate.py
dciclient/v1/shell_commands/pipeline.py
dciclient/v1/shell_commands/product.py
dciclient/v1/shell_commands/purge.py
dciclient/v1/shell_commands/remoteci.py
dciclient/v1/shell_commands/runner.py
dciclient/v1/shell_commands/team.py
dciclient/v1/shell_commands/topic.py
dciclient/v1/shell_commands/user.py
dciclient-4.1.0.post202510221005.dist-info/LICENSE
dciclient-4.1.0.post202510221005.dist-info/METADATA
dciclient-4.1.0.post202510221005.dist-info/WHEEL
dciclient-4.1.0.post202510221005.dist-info/entry_points.txt
dciclient-4.1.0.post202510221005.dist-info/top_level.txt
dciclient-4.1.0.post202510221005.dist-info/RECORD
