Metadata-Version: 2.1
Name: dciclient
Version: 4.1.0.post202510221005
Summary: Python client for DCI Control Server
Home-page: https://github.com/redhat-cip/python-dciclient
Author: Distributed CI team
Author-email: distributed-ci@redhat.com
License: Apache v2.0
Classifier: Environment :: Console
Classifier: Intended Audience :: Developers
Classifier: Intended Audience :: Information Technology
Classifier: License :: OSI Approved :: Apache Software License
Classifier: Operating System :: POSIX :: Linux
Classifier: Programming Language :: Python :: 2.7
Classifier: Programming Language :: Python :: 3.6
Classifier: Topic :: System :: Distributed Computing
License-File: LICENSE
Requires-Dist: PrettyTable <0.8,>=0.7.2
Requires-Dist: requests <3.0,>=2.20.0
Requires-Dist: dciauth
